{
  "servers": [
    "1.1.1.1",
    "8.8.8.8",
    {
      "address": "1.2.3.4",
      "port": 53,
      "domains": [
        "gemini.google.com",
        "deepmind.com",
        "deepmind.google",
        "generativeai.google",
        "geller-pa.googleapis.com",
        "generativelanguage.googleapis.com",
        "proactivebackend-pa.googleapis.com",
        "ai.google.dev",
        "alkalicore-pa.clients6.google.com",
        "alkalimakersuite-pa.clients6.google.com",
        "webchannel-alkalimakersuite-pa.clients6.google.com",
        "makersuite.google.com",
        "aistudio.google.com",
        "bard.google.com",
        "gemini.google",
        "notebooklm.google",
        "notebooklm.google.com",
        "jules.google",
        "jules.google.com",
        "labs.google",
        "geosite:google-deepmind"
      ]
    }
  ],
  "tag": "dns_inbound"
}
